Devmiko/__init__.py
Devmiko-0.0.3.dist-info/LICENSE
Devmiko-0.0.3.dist-info/METADATA
Devmiko-0.0.3.dist-info/WHEEL
Devmiko-0.0.3.dist-info/top_level.txt
Devmiko-0.0.3.dist-info/RECORD
