Metadata-Version: 2.1
Name: Devmiko
Version: 0.0.3
Summary: A SSH client for systems network automation that uses paramiko.
Home-page: https://github.com/vsantiago113/Devmiko
Author: Victor M Santiago
Author-email: vsantiago113sec@gmail.com
License: MIT
Download-URL: https://github.com/vsantiago113/Devmiko/archive/0.0.3.tar.gz
Keywords: paramiko,firepower,cisco,ftd,ssh
Platform: UNKNOWN
Classifier: Development Status :: 5 - Production/Stable
Classifier: Topic :: Utilities
Classifier: License :: OSI Approved :: MIT License
Classifier: Operating System :: MacOS :: MacOS X
Classifier: Operating System :: Microsoft :: Windows
Classifier: Operating System :: POSIX :: Linux
Classifier: Programming Language :: Python
Classifier: Intended Audience :: Developers
Classifier: Programming Language :: Python :: 3.4
Classifier: Programming Language :: Python :: 3.5
Classifier: Programming Language :: Python :: 3.6
Classifier: Programming Language :: Python :: 3.7
Classifier: Programming Language :: Python :: 3.8
Requires-Python: >=3.4.0
Requires-Dist: paramiko
Requires-Dist: tqdm
